LICENSE
MANIFEST.in
README.rst
flask_hmac.py
setup.py
Flask_HMAC.egg-info/PKG-INFO
Flask_HMAC.egg-info/SOURCES.txt
Flask_HMAC.egg-info/dependency_links.txt
Flask_HMAC.egg-info/not-zip-safe
Flask_HMAC.egg-info/requires.txt
Flask_HMAC.egg-info/top_level.txt