Metadata-Version: 1.1
Name: Flask-HMAC
Version: 0.1.1
Summary: Flask HMAC generator, checker, and route decorator
Home-page: http://github.com/jamonation/flask-hmac
Author: Jamon Camisso
Author-email: jamonation+flask@gmail.com
License: WTFPL
Platform: any
Classifier: Environment :: Web Environment
Classifier: Framework :: Flask
Classifier: Intended Audience :: Developers
Classifier: Operating System :: OS Independent
Classifier: Programming Language :: Python
Classifier: Topic :: Internet :: WWW/HTTP :: Dynamic Content
Classifier: Topic :: Security :: Cryptography
Classifier: Topic :: Software Development :: Libraries :: Python Modules
